bellhop/__init__.py
bellhop/apps.py
bellhop/engines.py
bellhop/main.py
bellhop/uploaders.py
bellhop-0.0.1.dist-info/METADATA
bellhop-0.0.1.dist-info/WHEEL
bellhop-0.0.1.dist-info/licenses/LICENSE
bellhop-0.0.1.dist-info/RECORD
