Metadata-Version: 2.1
Name: bellhop
Version: 0.0.1
Summary: Classy solution for file uploads in Django. Inspired by CarrierWave.
Project-URL: Homepage, https://github.com/sharshub/bellhop
Project-URL: Bug Tracker, https://github.com/sharshub/bellhop/issues
Author-email: Shubham Sharma <sharshub@users.noreply.github.com>
License-File: LICENSE
Classifier: License :: OSI Approved :: MIT License
Classifier: Operating System :: OS Independent
Classifier: Programming Language :: Python :: 3
Requires-Python: >=3.7
Requires-Dist: boto3>=1.26
Requires-Dist: django>=3.2
